{"type": "xviz/state_update", "data": {"update_type": "snapshot", "updates": [{"timestamp": 1016.2, "poses": {"/vehicle_pose": {"timestamp": 1016.2, "map_origin": {"longitude": 0, "latitude": 0, "altitude": 0}, "orientation": [0, 0, 0]}}, "primitives": {"/object/shape": {"polygons": [{"vertices": [[28.48, 2.06, 0], [32.28, 2.2, 0], [32.33, 0.58, 0], [28.53, 0.45, 0]], "base": {"object_id": "object-1", "style": {"fill_color": "#555", "height": 1.507424}}}, {"vertices": [[41.32, 5.74, 0], [45.34, 5.88, 0], [45.39, 4.26, 0], [41.38, 4.13, 0]], "base": {"object_id": "object-1", "style": {"fill_color": "#555", "height": 1.393504}}}, {"vertices": [[23.19, -11.12, 0], [23.61, -14.73, 0], [22.01, -14.92, 0], [21.58, -11.31, 0]], "base": {"object_id": "object-1", "style": {"fill_color": "#555", "height": 1.461854}}}, {"vertices": [[25.45, -23.24, 0], [24.83, -19.43, 0], [26.47, -19.16, 0], [27.09, -22.97, 0]], "base": {"object_id": "object-1", "style": {"fill_color": "#555", "height": 1.546396}}}]}, "/object/label": {"texts": [{"position": [30.403467, 1.322907, 1.707424], "text": "Car: 30 m"}, {"position": [43.356438, 5.004666, 1.593504], "text": "Car: 43 m"}, {"position": [22.598216, -13.020331, 1.661854], "text": "Car: 22 m"}, {"position": [25.961052, -21.198168, 1.746396], "text": "Car: 25 m"}]}, "/prediction/trajectory": {"polylines": []}}}]}}